PriceIndexCalc/__init__.py
PriceIndexCalc/version.py
PriceIndexCalc/pandas_modules/__init__.py
PriceIndexCalc/pandas_modules/bilateral.py
PriceIndexCalc/pandas_modules/chaining.py
PriceIndexCalc/pandas_modules/extension_methods.py
PriceIndexCalc/pandas_modules/helpers.py
PriceIndexCalc/pandas_modules/index_methods.py
PriceIndexCalc/pandas_modules/multilateral.py
PriceIndexCalc/pandas_modules/weighted_least_squares.py
PriceIndexCalc/pyspark_modules/__init__.py
PriceIndexCalc/pyspark_modules/chaining.py
PriceIndexCalc/pyspark_modules/helpers.py
PriceIndexCalc/pyspark_modules/index_methods.py
PriceIndexCalc/pyspark_modules/multilateral.py
PriceIndexCalc/pyspark_modules/native_spark_gk.py
PriceIndexCalc/pyspark_modules/weighted_least_squares.py
PriceIndexCalc2-0.8.0.dist-info/LICENSE
PriceIndexCalc2-0.8.0.dist-info/METADATA
PriceIndexCalc2-0.8.0.dist-info/WHEEL
PriceIndexCalc2-0.8.0.dist-info/top_level.txt
PriceIndexCalc2-0.8.0.dist-info/RECORD
